simp.py
simp-2.0.0.data/scripts/simp
simp-2.0.0.dist-info/LICENSE
simp-2.0.0.dist-info/METADATA
simp-2.0.0.dist-info/WHEEL
simp-2.0.0.dist-info/top_level.txt
simp-2.0.0.dist-info/RECORD
