Metadata-Version: 2.1
Name: simp
Version: 2.0.0
Summary: Sort imports simply
Home-page: https://github.com/rec/simp
Author: Tom Ritchford
Author-email: tom@swirly.com
License: MIT
Keywords: documentation
Platform: UNKNOWN
Classifier: Development Status :: 5 - Production/Stable
Classifier: Programming Language :: Python :: 3.6
Classifier: Programming Language :: Python :: 3.7
Classifier: Programming Language :: Python :: 3.8
Classifier: Programming Language :: Python :: 3.9
Classifier: Intended Audience :: Developers
Classifier: License :: OSI Approved :: MIT License
Classifier: Topic :: Software Development :: Libraries
Classifier: Topic :: Utilities
Requires-Dist: myers
